{
  "type": "FeatureCollection",
  "features": [
    {
      "type": "Feature",
      "geometry": {
        "type": "Polygon",
        "coordinates": [
          [
            [
              122.55552673400018,
              10.93789005200017
            ],
            [
              122.55783081100014,
              10.938619614000174
            ],
            [
              122.56017303400017,
              10.938839912000105
            ],
            [
              122.56257629400011,
              10.937379838000084
            ],
            [
              122.56419372500022,
              10.93560981800016
            ],
            [
              122.5654983510002,
              10.934249879000163
            ],
            [
              122.56903839200004,
              10.941949845000067
            ],
            [
              122.57391357500012,
              10.941479683000068
            ],
            [
              122.57382202100018,
              10.944020272000046
            ],
            [
              122.57302093600003,
              10.945940019000034
            ],
            [
              122.57122039900003,
              10.94793987300011
            ],
            [
              122.56683349600007,
              10.947250366000162
            ],
            [
              122.56381225700011,
              10.946619988000066
            ],
            [
              122.55921173100012,
              10.946120263000182
            ],
            [
              122.55857086100002,
              10.94367027300018
            ],
            [
              122.55758667000009,
              10.941670419000047
            ],
            [
              122.55666351200023,
              10.94009971600002
            ],
            [
              122.55552673400018,
              10.93789005200017
            ]
          ]
        ]
      },
      "properties": {
        "GID_3": "PHL.36.29.1_1",
        "GID_0": "PHL",
        "COUNTRY": "Philippines",
        "GID_1": "PHL.36_1",
        "NAME_1": "Iloilo",
        "NL_NAME_1": "NA",
        "GID_2": "PHL.36.29_1",
        "NAME_2": "Mina",
        "NL_NAME_2": "NA",
        "NAME_3": "Abat",
        "VARNAME_3": "NA",
        "NL_NAME_3": "NA",
        "TYPE_3": "Barangay",
        "ENGTYPE_3": "Village",
        "CC_3": "NA",
        "HASC_3": "NA"
      }
    },
    {
      "type": "Feature",
      "geometry": {
        "type": "Polygon",
        "coordinates": [
          [
            [
              122.60529327300003,
              10.907679559000144
            ],
            [
              122.61875152600021,
              10.913370133000058
            ],
            [
              122.62055206300022,
              10.918390273000114
            ],
            [
              122.61739349300001,
              10.923089981000146
            ],
            [
              122.61617279100005,
              10.923040391000143
            ],
            [
              122.61660766600005,
              10.924019814000076
            ],
            [
              122.61444091700014,
              10.924710274000176
            ],
            [
              122.61412048400018,
              10.92545032400011
            ],
            [
              122.609786987,
              10.928569793000065
            ],
            [
              122.61009979300013,
              10.930660248000095
            ],
            [
              122.60447692800005,
              10.92858028300003
            ],
            [
              122.5946426390002,
              10.91915988900007
            ],
            [
              122.5933074940001,
              10.915249824000114
            ],
            [
              122.5991134640002,
              10.910539628000095
            ],
            [
              122.6038970950001,
              10.90909004200006
            ],
            [
              122.60529327300003,
              10.907679559000144
            ]
          ]
        ]
      },
      "properties": {
        "GID_3": "PHL.36.29.2_1",
        "GID_0": "PHL",
        "COUNTRY": "Philippines",
        "GID_1": "PHL.36_1",
        "NAME_1": "Iloilo",
        "NL_NAME_1": "NA",
        "GID_2": "PHL.36.29_1",
        "NAME_2": "Mina",
        "NL_NAME_2": "NA",
        "NAME_3": "Agmanaphao",
        "VARNAME_3": "NA",
        "NL_NAME_3": "NA",
        "TYPE_3": "Barangay",
        "ENGTYPE_3": "Village",
        "CC_3": "NA",
        "HASC_3": "NA"
      }
    },
    {
      "type": "Feature",
      "geometry": {
        "type": "Polygon",
        "coordinates": [
          [
            [
              122.58326721100013,
              10.919610023000189
            ],
            [
              122.57407379100005,
              10.925600051000174
            ],
            [
              122.5701065070001,
              10.92467975600016
            ],
            [
              122.5537872320001,
              10.922900200000186
            ],
            [
              122.56384277300015,
              10.911589622000122
            ],
            [
              122.5711593640001,
              10.908060074000105
            ],
            [
              122.57730865400015,
              10.905220031000056
            ],
            [
              122.58113861100003,
              10.913749696000139
            ],
            [
              122.58326721100013,
              10.919610023000189
            ]
          ]
        ]
      },
      "properties": {
        "GID_3": "PHL.36.29.3_1",
        "GID_0": "PHL",
        "COUNTRY": "Philippines",
        "GID_1": "PHL.36_1",
        "NAME_1": "Iloilo",
        "NL_NAME_1": "NA",
        "GID_2": "PHL.36.29_1",
        "NAME_2": "Mina",
        "NL_NAME_2": "NA",
        "NAME_3": "Amiroy",
        "VARNAME_3": "NA",
        "NL_NAME_3": "NA",
        "TYPE_3": "Barangay",
        "ENGTYPE_3": "Village",
        "CC_3": "NA",
        "HASC_3": "NA"
      }
    },
    {
      "type": "Feature",
      "geometry": {
        "type": "Polygon",
        "coordinates": [
          [
            [
              122.5946426390002,
              10.91915988900007
            ],
            [
              122.58564758300008,
              10.923410416000081
            ],
            [
              122.58326721100013,
              10.919610023000189
            ],
            [
              122.58113861100003,
              10.913749696000139
            ],
            [
              122.57730865400015,
              10.905220031000056
            ],
            [
              122.58627319400023,
              10.90326023200015
            ],
            [
              122.58746337800005,
              10.903679849000127
            ],
            [
              122.59092712500023,
              10.903539657000124
            ],
            [
              122.59655761700003,
              10.900979995000057
            ],
            [
              122.60085296500017,
              10.900560380000059
            ],
            [
              122.60224151500006,
              10.900030136000055
            ],
            [
              122.60289764400011,
              10.898409844000128
            ],
            [
              122.6038970950001,
              10.896499635000055
            ],
            [
              122.60608673100012,
              10.895420074000185
            ],
            [
              122.60827636800002,
              10.896380424000085
            ],
            [
              122.60872650200008,
              10.896240235000107
            ],
            [
              122.60930633600015,
              10.89632034400006
            ],
            [
              122.6102676390002,
              10.896769525000025
            ],
            [
              122.61089325000012,
              10.896840096000062
            ],
            [
              122.61173248300008,
              10.89626026100018
            ],
            [
              122.61386871300022,
              10.895939826000017
            ],
            [
              122.61083984300012,
              10.90180015600015
            ],
            [
              122.60529327300003,
              10.907679559000144
            ],
            [
              122.6038970950001,
              10.90909004200006
            ],
            [
              122.5991134640002,
              10.910539628000095
            ],
            [
              122.5933074940001,
              10.915249824000114
            ],
            [
              122.5946426390002,
              10.91915988900007
            ]
          ]
        ]
      },
      "properties": {
        "GID_3": "PHL.36.29.4_1",
        "GID_0": "PHL",
        "COUNTRY": "Philippines",
        "GID_1": "PHL.36_1",
        "NAME_1": "Iloilo",
        "NL_NAME_1": "NA",
        "GID_2": "PHL.36.29_1",
        "NAME_2": "Mina",
        "NL_NAME_2": "NA",
        "NAME_3": "Badiangan",
        "VARNAME_3": "NA",
        "NL_NAME_3": "NA",
        "TYPE_3": "Barangay",
        "ENGTYPE_3": "Village",
        "CC_3": "NA",
        "HASC_3": "NA"
      }
    },
    {
      "type": "Feature",
      "geometry": {
        "type": "Polygon",
        "coordinates": [
          [
            [
              122.5654983510002,
              10.934249879000163
            ],
            [
              122.5674285890002,
              10.935250283000187
            ],
            [
              122.56951904200002,
              10.935540199000172
            ],
            [
              122.57080078200022,
              10.93502998300005
            ],
            [
              122.57241058300008,
              10.93416977000004
            ],
            [
              122.57431030400016,
              10.933950425000091
            ],
            [
              122.57543182400002,
              10.934069632999979
            ],
            [
              122.57584381100014,
              10.934249879000163
            ],
            [
              122.57620239300013,
              10.935159684000041
            ],
            [
              122.57646179200003,
              10.935580254000001
            ],
            [
              122.57711792000009,
              10.935170174000007
            ],
            [
              122.57804870600023,
              10.934419632000072
            ],
            [
              122.57803344800004,
              10.933560372000045
            ],
            [
              122.57814025800019,
              10.932700156000124
            ],
            [
              122.57840728800022,
              10.932359695000116
            ],
            [
              122.5795364390001,
              10.932570458000043
            ],
            [
              122.58007049600019,
              10.933569909000028
            ],
            [
              122.58146667400001,
              10.934920310000109
            ],
            [
              122.5816192640001,
              10.935669900000164
            ],
            [
              122.58187866100013,
              10.937319755000146
            ],
            [
              122.58173370400016,
              10.938269615000081
            ],
            [
              122.58103179900002,
              10.938779830999977
            ],
            [
              122.58001708900008,
              10.938449860000162
            ],
            [
              122.57890319900014,
              10.937749863000022
            ],
            [
              122.57800292900004,
              10.938349724000034
            ],
            [
              122.57810974200015,
              10.940050126000017
            ],
            [
              122.57469177200016,
              10.93824958900018
            ],
            [
              122.57391357500012,
              10.941479683000068
            ],
            [
              122.56903839200004,
              10.941949845000067
            ],
            [
              122.5654983510002,
              10.934249879000163
            ]
          ]
        ]
      },
      "properties": {
        "GID_3": "PHL.36.29.5_1",
        "GID_0": "PHL",
        "COUNTRY": "Philippines",
        "GID_1": "PHL.36_1",
        "NAME_1": "Iloilo",
        "NL_NAME_1": "NA",
        "GID_2": "PHL.36.29_1",
        "NAME_2": "Mina",
        "NL_NAME_2": "NA",
        "NAME_3": "Bangac",
        "VARNAME_3": "NA",
        "NL_NAME_3": "NA",
        "TYPE_3": "Barangay",
        "ENGTYPE_3": "Village",
        "CC_3": "NA",
        "HASC_3": "NA"
      }
    },
    {
      "type": "Feature",
      "geometry": {
        "type": "Polygon",
        "coordinates": [
          [
            [
              122.5795364390001,
              10.932570458000043
            ],
            [
              122.58670043900008,
              10.928819657000133
            ],
            [
              122.58989715700011,
              10.931019783000067
            ],
            [
              122.59467315600011,
              10.933170318000123
            ],
            [
              122.59555053700001,
              10.934570314000155
            ],
            [
              122.59153747600021,
              10.93859958700017
            ],
            [
              122.59008026100003,
              10.939849854000158
            ],
            [
              122.58850097600032,
              10.941180228999997
            ],
            [
              122.58651733400018,
              10.942330360000028
            ],
            [
              122.5840835570001,
              10.943050384000117
            ],
            [
              122.58258819700006,
              10.943059922000032
            ],
            [
              122.58094787500022,
              10.94169044500012
            ],
            [
              122.5794067380001,
              10.941129683999975
            ],
            [
              122.57810974200015,
              10.940050126000017
            ],
            [
              122.57800292900004,
              10.938349724000034
            ],
            [
              122.57890319900014,
              10.937749863000022
            ],
            [
              122.58001708900008,
              10.938449860000162
            ],
            [
              122.58103179900002,
              10.938779830999977
            ],
            [
              122.58173370400016,
              10.938269615000081
            ],
            [
              122.58187866100013,
              10.937319755000146
            ],
            [
              122.5816192640001,
              10.935669900000164
            ],
            [
              122.58146667400001,
              10.934920310000109
            ],
            [
              122.58007049600019,
              10.933569909000028
            ],
            [
              122.5795364390001,
              10.932570458000043
            ]
          ]
        ]
      },
      "properties": {
        "GID_3": "PHL.36.29.6_1",
        "GID_0": "PHL",
        "COUNTRY": "Philippines",
        "GID_1": "PHL.36_1",
        "NAME_1": "Iloilo",
        "NL_NAME_1": "NA",
        "GID_2": "PHL.36.29_1",
        "NAME_2": "Mina",
        "NL_NAME_2": "NA",
        "NAME_3": "Cabalabaguan",
        "VARNAME_3": "NA",
        "NL_NAME_3": "NA",
        "TYPE_3": "Barangay",
        "ENGTYPE_3": "Village",
        "CC_3": "NA",
        "HASC_3": "NA"
      }
    },
    {
      "type": "Feature",
      "geometry": {
        "type": "Polygon",
        "coordinates": [
          [
            [
              122.60044097800005,
              10.952440261000163
            ],
            [
              122.60539245600012,
              10.955129625000097
            ],
            [
              122.60633087200017,
              10.957329750000156
            ],
            [
              122.60678863600003,
              10.959210396000117
            ],
            [
              122.60749816900034,
              10.961190224000177
            ],
            [
              122.60551452600009,
              10.962114334999967
            ],
            [
              122.60459899800003,
              10.962539672000105
            ],
            [
              122.60341644300013,
              10.96243953700008
            ],
            [
              122.60233306900022,
              10.962650300000178
            ],
            [
              122.6008682260001,
              10.962650300000178
            ],
            [
              122.59850311300022,
              10.962989808000032
            ],
            [
              122.59681701600005,
              10.963430404000064
            ],
            [
              122.59493255500001,
              10.962470053999994
            ],
            [
              122.59282684400011,
              10.962140083000179
            ],
            [
              122.5911483760002,
              10.96243953700008
            ],
            [
              122.58919525100009,
              10.962114334999967
            ],
            [
              122.5889892570001,
              10.962080003000153
            ],
            [
              122.58886718800011,
              10.958219529000132
            ],
            [
              122.59384155200007,
              10.957819938
            ],
            [
              122.60044097800005,
              10.952440261000163
            ]
          ]
        ]
      },
      "properties": {
        "GID_3": "PHL.36.29.7_1",
        "GID_0": "PHL",
        "COUNTRY": "Philippines",
        "GID_1": "PHL.36_1",
        "NAME_1": "Iloilo",
        "NL_NAME_1": "NA",
        "GID_2": "PHL.36.29_1",
        "NAME_2": "Mina",
        "NL_NAME_2": "NA",
        "NAME_3": "Capul-An",
        "VARNAME_3": "NA",
        "NL_NAME_3": "NA",
        "TYPE_3": "Barangay",
        "ENGTYPE_3": "Village",
        "CC_3": "NA",
        "HASC_3": "NA"
      }
    },
    {
      "type": "Feature",
      "geometry": {
        "type": "Polygon",
        "coordinates": [
          [
            [
              122.60447692800005,
              10.92858028300003
            ],
            [
              122.59555053700001,
              10.934570314000155
            ],
            [
              122.59467315600011,
              10.933170318000123
            ],
            [
              122.58989715700011,
              10.931019783000067
            ],
            [
              122.58670043900008,
              10.928819657000133
            ],
            [
              122.58564758300008,
              10.923410416000081
            ],
            [
              122.5946426390002,
              10.91915988900007
            ],
            [
              122.60447692800005,
              10.92858028300003
            ]
          ]
        ]
      },
      "properties": {
        "GID_3": "PHL.36.29.8_1",
        "GID_0": "PHL",
        "COUNTRY": "Philippines",
        "GID_1": "PHL.36_1",
        "NAME_1": "Iloilo",
        "NL_NAME_1": "NA",
        "GID_2": "PHL.36.29_1",
        "NAME_2": "Mina",
        "NL_NAME_2": "NA",
        "NAME_3": "Dala",
        "VARNAME_3": "NA",
        "NL_NAME_3": "NA",
        "TYPE_3": "Barangay",
        "ENGTYPE_3": "Village",
        "CC_3": "NA",
        "HASC_3": "NA"
      }
    },
    {
      "type": "Feature",
      "geometry": {
        "type": "Polygon",
        "coordinates": [
          [
            [
              122.58422088600003,
              10.95820999200015
            ],
            [
              122.58025360000022,
              10.95339012100004
            ],
            [
              122.58257293600013,
              10.94773960100008
            ],
            [
              122.58339691200024,
              10.94820976300008
            ],
            [
              122.58455657900004,
              10.947699547000127
            ],
            [
              122.58605957000009,
              10.94727993000015
            ],
            [
              122.58818054100004,
              10.94769001100002
            ],
            [
              122.58995056200001,
              10.948710441999992
            ],
            [
              122.59129333500016,
              10.95083046100018
            ],
            [
              122.58882904100005,
              10.952850343000136
            ],
            [
              122.58422088600003,
              10.95820999200015
            ]
          ]
        ]
      },
      "properties": {
        "GID_3": "PHL.36.29.9_1",
        "GID_0": "PHL",
        "COUNTRY": "Philippines",
        "GID_1": "PHL.36_1",
        "NAME_1": "Iloilo",
        "NL_NAME_1": "NA",
        "GID_2": "PHL.36.29_1",
        "NAME_2": "Mina",
        "NL_NAME_2": "NA",
        "NAME_3": "Guibuangan",
        "VARNAME_3": "NA",
        "NL_NAME_3": "NA",
        "TYPE_3": "Barangay",
        "ENGTYPE_3": "Village",
        "CC_3": "NA",
        "HASC_3": "NA"
      }
    },
    {
      "type": "Feature",
      "geometry": {
        "type": "Polygon",
        "coordinates": [
          [
            [
              122.57730865400015,
              10.905220031000056
            ],
            [
              122.57163238600015,
              10.90441036300001
            ],
            [
              122.56897735600035,
              10.904009819000123
            ],
            [
              122.56594085700021,
              10.903160095000146
            ],
            [
              122.56452179000007,
              10.902170181000145
            ],
            [
              122.56522369300001,
              10.901479720999987
            ],
            [
              122.56636047400002,
              10.90116024100007
            ],
            [
              122.56819915800008,
              10.900329590000126
            ],
            [
              122.56752777100007,
              10.899330140000075
            ],
            [
              122.56729126000027,
              10.898670197000058
            ],
            [
              122.56591796800001,
              10.897919654000077
            ],
            [
              122.56629180800019,
              10.896739961000037
            ],
            [
              122.56815338100012,
              10.897120475999998
            ],
            [
              122.56964874300002,
              10.896499635000055
            ],
            [
              122.57026672400013,
              10.895589830000006
            ],
            [
              122.57209777800006,
              10.895299911000109
            ],
            [
              122.57447051900022,
              10.896149636000132
            ],
            [
              122.57515716600005,
              10.897379876000173
            ],
            [
              122.57557678300009,
              10.898730279000063
            ],
            [
              122.57608032200005,
              10.898900031999972
            ],
            [
              122.57666015600012,
              10.898480414999995
            ],
            [
              122.57713317900004,
              10.897020339000164
            ],
            [
              122.5774536140002,
              10.89573955700007
            ],
            [
              122.57819366400031,
              10.89412021600009
            ],
            [
              122.58027648900008,
              10.89391994400006
            ],
            [
              122.58209991400008,
              10.893460275000109
            ],
            [
              122.58370971700015,
              10.894559861000175
            ],
            [
              122.58326721100013,
              10.896389962000171
            ],
            [
              122.58383941600005,
              10.897159576000035
            ],
            [
              122.58497619600018,
              10.898050308000052
            ],
            [
              122.58627319400023,
              10.90326023200015
            ],
            [
              122.57730865400015,
              10.905220031000056
            ]
          ]
        ]
      },
      "properties": {
        "GID_3": "PHL.36.29.10_1",
        "GID_0": "PHL",
        "COUNTRY": "Philippines",
        "GID_1": "PHL.36_1",
        "NAME_1": "Iloilo",
        "NL_NAME_1": "NA",
        "GID_2": "PHL.36.29_1",
        "NAME_2": "Mina",
        "NL_NAME_2": "NA",
        "NAME_3": "Janipa-An East",
        "VARNAME_3": "NA",
        "NL_NAME_3": "NA",
        "TYPE_3": "Barangay",
        "ENGTYPE_3": "Village",
        "CC_3": "NA",
        "HASC_3": "NA"
      }
    },
    {
      "type": "Feature",
      "geometry": {
        "type": "Polygon",
        "coordinates": [
          [
            [
              122.55132293700001,
              10.917610169000056
            ],
            [
              122.5515213010001,
              10.914859773000046
            ],
            [
              122.55219268800033,
              10.913539886000024
            ],
            [
              122.5528869630001,
              10.913709641000082
            ],
            [
              122.55297088600003,
              10.913240432000123
            ],
            [
              122.55264282100018,
              10.912859917000162
            ],
            [
              122.55413055300005,
              10.911939621000045
            ],
            [
              122.5556335440001,
              10.910110473000032
            ],
            [
              122.55615997300004,
              10.909219741000072
            ],
            [
              122.55608368000003,
              10.908289910000121
            ],
            [
              122.5570220940001,
              10.906379700000173
            ],
            [
              122.55795288000002,
              10.905079842000077
            ],
            [
              122.557929994,
              10.904009819000123
            ],
            [
              122.55790710500003,
              10.902640343000144
            ],
            [
              122.55877685600012,
              10.902359962000105
            ],
            [
              122.55975341700002,
              10.901639938000017
            ],
            [
              122.56034851000015,
              10.900509835000037
            ],
            [
              122.5616226190001,
              10.90102004900018
            ],
            [
              122.56311035200008,
              10.902219773000127
            ],
            [
              122.56452179000007,
              10.902170181000145
            ],
            [
              122.56594085700021,
              10.903160095000146
            ],
            [
              122.56897735600035,
              10.904009819000123
            ],
            [
              122.57163238600015,
              10.90441036300001
            ],
            [
              122.57730865400015,
              10.905220031000056
            ],
            [
              122.5711593640001,
              10.908060074000105
            ],
            [
              122.56384277300015,
              10.911589622000122
            ],
            [
              122.5537872320001,
              10.922900200000186
            ],
            [
              122.55132293700001,
              10.917610169000056
            ]
          ]
        ]
      },
      "properties": {
        "GID_3": "PHL.36.29.11_1",
        "GID_0": "PHL",
        "COUNTRY": "Philippines",
        "GID_1": "PHL.36_1",
        "NAME_1": "Iloilo",
        "NL_NAME_1": "NA",
        "GID_2": "PHL.36.29_1",
        "NAME_2": "Mina",
        "NL_NAME_2": "NA",
        "NAME_3": "Janipa-An West",
        "VARNAME_3": "NA",
        "NL_NAME_3": "NA",
        "TYPE_3": "Barangay",
        "ENGTYPE_3": "Village",
        "CC_3": "NA",
        "HASC_3": "NA"
      }
    },
    {
      "type": "Feature",
      "geometry": {
        "type": "Polygon",
        "coordinates": [
          [
            [
              122.57543182400002,
              10.934069632999979
            ],
            [
              122.57634735200031,
              10.932330131000128
            ],
            [
              122.57659149100004,
              10.930720329000167
            ],
            [
              122.57660675100021,
              10.926719666000167
            ],
            [
              122.58670043900008,
              10.928819657000133
            ],
            [
              122.5795364390001,
              10.932570458000043
            ],
            [
              122.57840728800022,
              10.932359695000116
            ],
            [
              122.57814025800019,
              10.932700156000124
            ],
            [
              122.57803344800004,
              10.933560372000045
            ],
            [
              122.57804870600023,
              10.934419632000072
            ],
            [
              122.57711792000009,
              10.935170174000007
            ],
            [
              122.57646179200003,
              10.935580254000001
            ],
            [
              122.57620239300013,
              10.935159684000041
            ],
            [
              122.57584381100014,
              10.934249879000163
            ],
            [
              122.57543182400002,
              10.934069632999979
            ]
          ]
        ]
      },
      "properties": {
        "GID_3": "PHL.36.29.12_1",
        "GID_0": "PHL",
        "COUNTRY": "Philippines",
        "GID_1": "PHL.36_1",
        "NAME_1": "Iloilo",
        "NL_NAME_1": "NA",
        "GID_2": "PHL.36.29_1",
        "NAME_2": "Mina",
        "NL_NAME_2": "NA",
        "NAME_3": "Mina East",
        "VARNAME_3": "Poblacion",
        "NL_NAME_3": "NA",
        "TYPE_3": "Barangay",
        "ENGTYPE_3": "Village",
        "CC_3": "NA",
        "HASC_3": "NA"
      }
    },
    {
      "type": "Feature",
      "geometry": {
        "type": "Polygon",
        "coordinates": [
          [
            [
              122.57407379100005,
              10.925600051000174
            ],
            [
              122.57660675100021,
              10.926719666000167
            ],
            [
              122.57659149100004,
              10.930720329000167
            ],
            [
              122.57634735200031,
              10.932330131000128
            ],
            [
              122.57543182400002,
              10.934069632999979
            ],
            [
              122.57431030400016,
              10.933950425000091
            ],
            [
              122.57241058300008,
              10.93416977000004
            ],
            [
              122.57080078200022,
              10.93502998300005
            ],
            [
              122.56951904200002,
              10.935540199000172
            ],
            [
              122.5674285890002,
              10.935250283000187
            ],
            [
              122.5654983510002,
              10.934249879000163
            ],
            [
              122.56726837100007,
              10.930319787000087
            ],
            [
              122.5701065070001,
              10.92467975600016
            ],
            [
              122.57407379100005,
              10.925600051000174
            ]
          ]
        ]
      },
      "properties": {
        "GID_3": "PHL.36.29.13_1",
        "GID_0": "PHL",
        "COUNTRY": "Philippines",
        "GID_1": "PHL.36_1",
        "NAME_1": "Iloilo",
        "NL_NAME_1": "NA",
        "GID_2": "PHL.36.29_1",
        "NAME_2": "Mina",
        "NL_NAME_2": "NA",
        "NAME_3": "Mina West",
        "VARNAME_3": "Poblacion",
        "NL_NAME_3": "NA",
        "TYPE_3": "Barangay",
        "ENGTYPE_3": "Village",
        "CC_3": "NA",
        "HASC_3": "NA"
      }
    },
    {
      "type": "Feature",
      "geometry": {
        "type": "Polygon",
        "coordinates": [
          [
            [
              122.58886718800011,
              10.958219529000132
            ],
            [
              122.58422088600003,
              10.95820999200015
            ],
            [
              122.58882904100005,
              10.952850343000136
            ],
            [
              122.59129333500016,
              10.95083046100018
            ],
            [
              122.59277343700023,
              10.95100021400009
            ],
            [
              122.59409332300004,
              10.951470376000088
            ],
            [
              122.59494018600003,
              10.951910019000138
            ],
            [
              122.59552002000021,
              10.951169966999998
            ],
            [
              122.59564971900022,
              10.94978046400007
            ],
            [
              122.5973205570001,
              10.950480462000087
            ],
            [
              122.59864044200015,
              10.951199531000157
            ],
            [
              122.60044097800005,
              10.952440261000163
            ],
            [
              122.59384155200007,
              10.957819938
            ],
            [
              122.58886718800011,
              10.958219529000132
            ]
          ]
        ]
      },
      "properties": {
        "GID_3": "PHL.36.29.14_1",
        "GID_0": "PHL",
        "COUNTRY": "Philippines",
        "GID_1": "PHL.36_1",
        "NAME_1": "Iloilo",
        "NL_NAME_1": "NA",
        "GID_2": "PHL.36.29_1",
        "NAME_2": "Mina",
        "NL_NAME_2": "NA",
        "NAME_3": "Nasirum",
        "VARNAME_3": "NA",
        "NL_NAME_3": "NA",
        "TYPE_3": "Barangay",
        "ENGTYPE_3": "Village",
        "CC_3": "NA",
        "HASC_3": "NA"
      }
    },
    {
      "type": "Feature",
      "geometry": {
        "type": "Polygon",
        "coordinates": [
          [
            [
              122.55921173100012,
              10.946120263000182
            ],
            [
              122.56381225700011,
              10.946619988000066
            ],
            [
              122.56683349600007,
              10.947250366000162
            ],
            [
              122.57122039900003,
              10.94793987300011
            ],
            [
              122.57125854600008,
              10.949150085000042
            ],
            [
              122.57212066600005,
              10.951009751000072
            ],
            [
              122.57218933200022,
              10.952480316000162
            ],
            [
              122.57068634100006,
              10.954500198000119
            ],
            [
              122.56923675600001,
              10.95526027600016
            ],
            [
              122.56340026800001,
              10.955710412000087
            ],
            [
              122.56347656300022,
              10.953639985000109
            ],
            [
              122.56286621000004,
              10.951660157000106
            ],
            [
              122.56150054900002,
              10.949310302000072
            ],
            [
              122.55921173100012,
              10.946120263000182
            ]
          ]
        ]
      },
      "properties": {
        "GID_3": "PHL.36.29.15_1",
        "GID_0": "PHL",
        "COUNTRY": "Philippines",
        "GID_1": "PHL.36_1",
        "NAME_1": "Iloilo",
        "NL_NAME_1": "NA",
        "GID_2": "PHL.36.29_1",
        "NAME_2": "Mina",
        "NL_NAME_2": "NA",
        "NAME_3": "Naumuan",
        "VARNAME_3": "NA",
        "NL_NAME_3": "NA",
        "TYPE_3": "Barangay",
        "ENGTYPE_3": "Village",
        "CC_3": "NA",
        "HASC_3": "NA"
      }
    },
    {
      "type": "Feature",
      "geometry": {
        "type": "Polygon",
        "coordinates": [
          [
            [
              122.58326721100013,
              10.919610023000189
            ],
            [
              122.58564758300008,
              10.923410416000081
            ],
            [
              122.58670043900008,
              10.928819657000133
            ],
            [
              122.57660675100021,
              10.926719666000167
            ],
            [
              122.57407379100005,
              10.925600051000174
            ],
            [
              122.58326721100013,
              10.919610023000189
            ]
          ]
        ]
      },
      "properties": {
        "GID_3": "PHL.36.29.16_1",
        "GID_0": "PHL",
        "COUNTRY": "Philippines",
        "GID_1": "PHL.36_1",
        "NAME_1": "Iloilo",
        "NL_NAME_1": "NA",
        "GID_2": "PHL.36.29_1",
        "NAME_2": "Mina",
        "NL_NAME_2": "NA",
        "NAME_3": "Singay",
        "VARNAME_3": "NA",
        "NL_NAME_3": "NA",
        "TYPE_3": "Barangay",
        "ENGTYPE_3": "Village",
        "CC_3": "NA",
        "HASC_3": "NA"
      }
    },
    {
      "type": "Feature",
      "geometry": {
        "type": "Polygon",
        "coordinates": [
          [
            [
              122.57391357500012,
              10.941479683000068
            ],
            [
              122.57469177200016,
              10.93824958900018
            ],
            [
              122.57810974200015,
              10.940050126000017
            ],
            [
              122.5794067380001,
              10.941129683999975
            ],
            [
              122.58094787500022,
              10.94169044500012
            ],
            [
              122.58258819700006,
              10.943059922000032
            ],
            [
              122.58296966500018,
              10.944140435000179
            ],
            [
              122.58315277100007,
              10.945529938000107
            ],
            [
              122.58257293600013,
              10.94773960100008
            ],
            [
              122.58025360000022,
              10.95339012100004
            ],
            [
              122.57584381100014,
              10.954070092000109
            ],
            [
              122.57264709600008,
              10.954440117000047
            ],
            [
              122.57068634100006,
              10.954500198000119
            ],
            [
              122.57218933200022,
              10.952480316000162
            ],
            [
              122.57212066600005,
              10.951009751000072
            ],
            [
              122.57125854600008,
              10.949150085000042
            ],
            [
              122.57122039900003,
              10.94793987300011
            ],
            [
              122.57302093600003,
              10.945940019000034
            ],
            [
              122.57382202100018,
              10.944020272000046
            ],
            [
              122.57391357500012,
              10.941479683000068
            ]
          ]
        ]
      },
      "properties": {
        "GID_3": "PHL.36.29.17_1",
        "GID_0": "PHL",
        "COUNTRY": "Philippines",
        "GID_1": "PHL.36_1",
        "NAME_1": "Iloilo",
        "NL_NAME_1": "NA",
        "GID_2": "PHL.36.29_1",
        "NAME_2": "Mina",
        "NL_NAME_2": "NA",
        "NAME_3": "Talibong Grande",
        "VARNAME_3": "NA",
        "NL_NAME_3": "NA",
        "TYPE_3": "Barangay",
        "ENGTYPE_3": "Village",
        "CC_3": "NA",
        "HASC_3": "NA"
      }
    },
    {
      "type": "Feature",
      "geometry": {
        "type": "Polygon",
        "coordinates": [
          [
            [
              122.5889892570001,
              10.962080003000153
            ],
            [
              122.58754730200008,
              10.961819648000187
            ],
            [
              122.58554077200017,
              10.96096038800016
            ],
            [
              122.5843429570001,
              10.960160256000052
            ],
            [
              122.57884216400032,
              10.961500168000043
            ],
            [
              122.5761413570001,
              10.959770202000072
            ],
            [
              122.57359314000018,
              10.95773983000015
            ],
            [
              122.57068634100006,
              10.954500198000119
            ],
            [
              122.57264709600008,
              10.954440117000047
            ],
            [
              122.57584381100014,
              10.954070092000109
            ],
            [
              122.58025360000022,
              10.95339012100004
            ],
            [
              122.58422088600003,
              10.95820999200015
            ],
            [
              122.58886718800011,
              10.958219529000132
            ],
            [
              122.5889892570001,
              10.962080003000153
            ]
          ]
        ]
      },
      "properties": {
        "GID_3": "PHL.36.29.18_1",
        "GID_0": "PHL",
        "COUNTRY": "Philippines",
        "GID_1": "PHL.36_1",
        "NAME_1": "Iloilo",
        "NL_NAME_1": "NA",
        "GID_2": "PHL.36.29_1",
        "NAME_2": "Mina",
        "NL_NAME_2": "NA",
        "NAME_3": "Talibong Pequeño",
        "VARNAME_3": "NA",
        "NL_NAME_3": "NA",
        "TYPE_3": "Barangay",
        "ENGTYPE_3": "Village",
        "CC_3": "NA",
        "HASC_3": "NA"
      }
    },
    {
      "type": "Feature",
      "geometry": {
        "type": "Polygon",
        "coordinates": [
          [
            [
              122.5627517700002,
              10.957059860000186
            ],
            [
              122.56340026800001,
              10.955710412000087
            ],
            [
              122.56923675600001,
              10.95526027600016
            ],
            [
              122.57068634100006,
              10.954500198000119
            ],
            [
              122.57359314000018,
              10.95773983000015
            ],
            [
              122.5761413570001,
              10.959770202000072
            ],
            [
              122.57884216400032,
              10.961500168000043
            ],
            [
              122.57621002300004,
              10.962114334999967
            ],
            [
              122.57391357500012,
              10.962650300000178
            ],
            [
              122.57063293400006,
              10.962949754000078
            ],
            [
              122.56900024500021,
              10.965510369000128
            ],
            [
              122.56839752200017,
              10.964610099000083
            ],
            [
              122.5674514770003,
              10.965000152000073
            ],
            [
              122.56558990500014,
              10.964039802000059
            ],
            [
              122.56535339400034,
              10.963089943000057
            ],
            [
              122.56416320800008,
              10.962220192000132
            ],
            [
              122.56403350800008,
              10.962114334999967
            ],
            [
              122.56272125300006,
              10.961009979999972
            ],
            [
              122.56272888100023,
              10.959219934000032
            ],
            [
              122.5627517700002,
              10.957059860000186
            ]
          ]
        ]
      },
      "properties": {
        "GID_3": "PHL.36.29.19_1",
        "GID_0": "PHL",
        "COUNTRY": "Philippines",
        "GID_1": "PHL.36_1",
        "NAME_1": "Iloilo",
        "NL_NAME_1": "NA",
        "GID_2": "PHL.36.29_1",
        "NAME_2": "Mina",
        "NL_NAME_2": "NA",
        "NAME_3": "Tipolo",
        "VARNAME_3": "NA",
        "NL_NAME_3": "NA",
        "TYPE_3": "Barangay",
        "ENGTYPE_3": "Village",
        "CC_3": "NA",
        "HASC_3": "NA"
      }
    },
    {
      "type": "Feature",
      "geometry": {
        "type": "Polygon",
        "coordinates": [
          [
            [
              122.5537872320001,
              10.922900200000186
            ],
            [
              122.5701065070001,
              10.92467975600016
            ],
            [
              122.56726837100007,
              10.930319787000087
            ],
            [
              122.5654983510002,
              10.934249879000163
            ],
            [
              122.56419372500022,
              10.93560981800016
            ],
            [
              122.56257629400011,
              10.937379838000084
            ],
            [
              122.56017303400017,
              10.938839912000105
            ],
            [
              122.55783081100014,
              10.938619614000174
            ],
            [
              122.55552673400018,
              10.93789005200017
            ],
            [
              122.55486297500022,
              10.935540199000172
            ],
            [
              122.55565643200009,
              10.932740211000123
            ],
            [
              122.55526733400018,
              10.930080414000088
            ],
            [
              122.55519104000007,
              10.928000451000003
            ],
            [
              122.5545272820001,
              10.926170350000007
            ],
            [
              122.5537872320001,
              10.922900200000186
            ]
          ]
        ]
      },
      "properties": {
        "GID_3": "PHL.36.29.20_1",
        "GID_0": "PHL",
        "COUNTRY": "Philippines",
        "GID_1": "PHL.36_1",
        "NAME_1": "Iloilo",
        "NL_NAME_1": "NA",
        "GID_2": "PHL.36.29_1",
        "NAME_2": "Mina",
        "NL_NAME_2": "NA",
        "NAME_3": "Tolarucan",
        "VARNAME_3": "NA",
        "NL_NAME_3": "NA",
        "TYPE_3": "Barangay",
        "ENGTYPE_3": "Village",
        "CC_3": "NA",
        "HASC_3": "NA"
      }
    },
    {
      "type": "Feature",
      "geometry": {
        "type": "Polygon",
        "coordinates": [
          [
            [
              122.59555053700001,
              10.934570314000155
            ],
            [
              122.59796905500025,
              10.943880082000021
            ],
            [
              122.60034179600007,
              10.94443988900008
            ],
            [
              122.60037231500019,
              10.947019577000162
            ],
            [
              122.60054779100005,
              10.947879792000037
            ],
            [
              122.60167694100005,
              10.947890283000106
            ],
            [
              122.60201263400006,
              10.948229789000095
            ],
            [
              122.60250854500032,
              10.94978046400007
            ],
            [
              122.60167694100005,
              10.950849534000042
            ],
            [
              122.60044097800005,
              10.952440261000163
            ],
            [
              122.59864044200015,
              10.951199531000157
            ],
            [
              122.5973205570001,
              10.950480462000087
            ],
            [
              122.59564971900022,
              10.94978046400007
            ],
            [
              122.59552002000021,
              10.951169966999998
            ],
            [
              122.59494018600003,
              10.951910019000138
            ],
            [
              122.59409332300004,
              10.951470376000088
            ],
            [
              122.59277343700023,
              10.95100021400009
            ],
            [
              122.59129333500016,
              10.95083046100018
            ],
            [
              122.58995056200001,
              10.948710441999992
            ],
            [
              122.58818054100004,
              10.94769001100002
            ],
            [
              122.58605957000009,
              10.94727993000015
            ],
            [
              122.58455657900004,
              10.947699547000127
            ],
            [
              122.58339691200024,
              10.94820976300008
            ],
            [
              122.58257293600013,
              10.94773960100008
            ],
            [
              122.58315277100007,
              10.945529938000107
            ],
            [
              122.58296966500018,
              10.944140435000179
            ],
            [
              122.58258819700006,
              10.943059922000032
            ],
            [
              122.5840835570001,
              10.943050384000117
            ],
            [
              122.58651733400018,
              10.942330360000028
            ],
            [
              122.58850097600032,
              10.941180228999997
            ],
            [
              122.59008026100003,
              10.939849854000158
            ],
            [
              122.59153747600021,
              10.93859958700017
            ],
            [
              122.59555053700001,
              10.934570314000155
            ]
          ]
        ]
      },
      "properties": {
        "GID_3": "PHL.36.29.21_1",
        "GID_0": "PHL",
        "COUNTRY": "Philippines",
        "GID_1": "PHL.36_1",
        "NAME_1": "Iloilo",
        "NL_NAME_1": "NA",
        "GID_2": "PHL.36.29_1",
        "NAME_2": "Mina",
        "NL_NAME_2": "NA",
        "NAME_3": "Tumay",
        "VARNAME_3": "NA",
        "NL_NAME_3": "NA",
        "TYPE_3": "Barangay",
        "ENGTYPE_3": "Village",
        "CC_3": "NA",
        "HASC_3": "NA"
      }
    },
    {
      "type": "Feature",
      "geometry": {
        "type": "Polygon",
        "coordinates": [
          [
            [
              122.56900024500021,
              10.965510369000128
            ],
            [
              122.57063293400006,
              10.962949754000078
            ],
            [
              122.57391357500012,
              10.962650300000178
            ],
            [
              122.57621002300004,
              10.962114334999967
            ],
            [
              122.57884216400032,
              10.961500168000043
            ],
            [
              122.5843429570001,
              10.960160256000052
            ],
            [
              122.58371734700006,
              10.960789680000062
            ],
            [
              122.58381652900005,
              10.961819648000187
            ],
            [
              122.58394622800006,
              10.962114334999967
            ],
            [
              122.58454132100019,
              10.963450432000116
            ],
            [
              122.58557128900009,
              10.965009689999988
            ],
            [
              122.58563232400013,
              10.966870308000125
            ],
            [
              122.58856964200015,
              10.968099595000126
            ],
            [
              122.58878326400009,
              10.969400406000034
            ],
            [
              122.58484649700006,
              10.970379829000137
            ],
            [
              122.58422851600017,
              10.97262954700011
            ],
            [
              122.5839233390002,
              10.973349571000028
            ],
            [
              122.58200836200012,
              10.972310066999967
            ],
            [
              122.57819366400031,
              10.9720001230001
            ],
            [
              122.57560730000023,
              10.971280099000012
            ],
            [
              122.57382202100018,
              10.96984958700017
            ],
            [
              122.57367706400021,
              10.969070435000162
            ],
            [
              122.57145691000017,
              10.968480110000087
            ],
            [
              122.57045745800008,
              10.967340469000021
            ],
            [
              122.56947326700003,
              10.966389657000036
            ],
            [
              122.56900024500021,
              10.965510369000128
            ]
          ]
        ]
      },
      "properties": {
        "GID_3": "PHL.36.29.22_1",
        "GID_0": "PHL",
        "COUNTRY": "Philippines",
        "GID_1": "PHL.36_1",
        "NAME_1": "Iloilo",
        "NL_NAME_1": "NA",
        "GID_2": "PHL.36.29_1",
        "NAME_2": "Mina",
        "NL_NAME_2": "NA",
        "NAME_3": "Yugot",
        "VARNAME_3": "NA",
        "NL_NAME_3": "NA",
        "TYPE_3": "Barangay",
        "ENGTYPE_3": "Village",
        "CC_3": "NA",
        "HASC_3": "NA"
      }
    }
  ]
}