{
  "type": "FeatureCollection",
  "features": [
    {
      "type": "Feature",
      "geometry": {
        "type": "Polygon",
        "coordinates": [
          [
            [
              120.86868286200001,
              17.111709595000093
            ],
            [
              120.86887359600018,
              17.108339310000076
            ],
            [
              120.88128662000031,
              17.111829758
            ],
            [
              120.88094329900002,
              17.11428070100004
            ],
            [
              120.88079834000007,
              17.115560533000064
            ],
            [
              120.87963104200014,
              17.125049590000117
            ],
            [
              120.86958312900003,
              17.116149903000178
            ],
            [
              120.86868286200001,
              17.111709595000093
            ]
          ]
        ]
      },
      "properties": {
        "GID_3": "PHL.50.3.1_1",
        "GID_0": "PHL",
        "COUNTRY": "Philippines",
        "GID_1": "PHL.50_1",
        "NAME_1": "Mountain Province",
        "NL_NAME_1": "NA",
        "GID_2": "PHL.50.3_1",
        "NAME_2": "Besao",
        "NL_NAME_2": "NA",
        "NAME_3": "Agawa",
        "VARNAME_3": "NA",
        "NL_NAME_3": "NA",
        "TYPE_3": "Barangay",
        "ENGTYPE_3": "Village",
        "CC_3": "NA",
        "HASC_3": "NA"
      }
    },
    {
      "type": "Feature",
      "geometry": {
        "type": "Polygon",
        "coordinates": [
          [
            [
              120.85827636700003,
              17.188180923000175
            ],
            [
              120.85764312700007,
              17.187379838000084
            ],
            [
              120.85569000300029,
              17.18530082799998
            ],
            [
              120.85047149600007,
              17.18166923600006
            ],
            [
              120.84429168700012,
              17.178409576000035
            ],
            [
              120.83545684800015,
              17.17296028200019
            ],
            [
              120.81440734900013,
              17.15637016300019
            ],
            [
              120.83419036800001,
              17.100570678000167
            ],
            [
              120.83550262500012,
              17.100610733000167
            ],
            [
              120.83696746800013,
              17.101270676000127
            ],
            [
              120.83750152600021,
              17.10164070100012
            ],
            [
              120.83817291200035,
              17.101739883000164
            ],
            [
              120.83939361500018,
              17.10165977400004
            ],
            [
              120.84068298300008,
              17.101289749000046
            ],
            [
              120.84387970000023,
              17.101650239000037
            ],
            [
              120.84612274200015,
              17.10224914700001
            ],
            [
              120.84763336100002,
              17.10288047900002
            ],
            [
              120.84809875500014,
              17.103229523000152
            ],
            [
              120.84884643500004,
              17.104249955
            ],
            [
              120.84973907400001,
              17.105800628000168
            ],
            [
              120.85025787400002,
              17.10692977900004
            ],
            [
              120.8510437010001,
              17.108709335000015
            ],
            [
              120.85228729300013,
              17.110050202000025
            ],
            [
              120.85513305700022,
              17.111089706000087
            ],
            [
              120.85727691700015,
              17.110839843999997
            ],
            [
              120.85855865500002,
              17.11042022700019
            ],
            [
              120.85928344700005,
              17.110269546999973
            ],
            [
              120.86052704000008,
              17.111059189000116
            ],
            [
              120.86160278300031,
              17.11222076400003
            ],
            [
              120.86280822700007,
              17.113410950000116
            ],
            [
              120.86341858000003,
              17.114259720000177
            ],
            [
              120.86392211900022,
              17.11603927600015
            ],
            [
              120.86396026600005,
              17.116840363000108
            ],
            [
              120.86389160200008,
              17.118890762000035
            ],
            [
              120.86411285300017,
              17.120899200999986
            ],
            [
              120.86437225300017,
              17.122949599000037
            ],
            [
              120.86415863000013,
              17.125270843000067
            ],
            [
              120.86389923000002,
              17.127119065000045
            ],
            [
              120.86354064900024,
              17.12863922100007
            ],
            [
              120.8644332880001,
              17.131010057000083
            ],
            [
              120.86451721200001,
              17.133169175000035
            ],
            [
              120.86440277100019,
              17.134609222999984
            ],
            [
              120.86441039900012,
              17.13497924800015
            ],
            [
              120.86431121700002,
              17.13715934800007
            ],
            [
              120.86461639400022,
              17.14118003900012
            ],
            [
              120.86634826700003,
              17.145589828000027
            ],
            [
              120.87728881800012,
              17.189260484000044
            ],
            [
              120.86492919900002,
              17.188779830999977
            ],
            [
              120.85827636700003,
              17.188180923000175
            ]
          ]
        ]
      },
      "properties": {
        "GID_3": "PHL.50.3.2_1",
        "GID_0": "PHL",
        "COUNTRY": "Philippines",
        "GID_1": "PHL.50_1",
        "NAME_1": "Mountain Province",
        "NL_NAME_1": "NA",
        "GID_2": "PHL.50.3_1",
        "NAME_2": "Besao",
        "NL_NAME_2": "NA",
        "NAME_3": "Ambaguio",
        "VARNAME_3": "NA",
        "NL_NAME_3": "NA",
        "TYPE_3": "Barangay",
        "ENGTYPE_3": "Village",
        "CC_3": "NA",
        "HASC_3": "NA"
      }
    },
    {
      "type": "Feature",
      "geometry": {
        "type": "Polygon",
        "coordinates": [
          [
            [
              120.85868835400015,
              17.08179092299997
            ],
            [
              120.8570327760001,
              17.082170486000052
            ],
            [
              120.85498809800004,
              17.082860946000153
            ],
            [
              120.85315704400011,
              17.083269120000182
            ],
            [
              120.8510971080002,
              17.084100724000052
            ],
            [
              120.8495025630001,
              17.085300445000087
            ],
            [
              120.84809112500022,
              17.086080552000112
            ],
            [
              120.84703064000018,
              17.087240219000023
            ],
            [
              120.84639740000011,
              17.087720870999988
            ],
            [
              120.84414672900004,
              17.08735084600005
            ],
            [
              120.84236907900004,
              17.08691024799998
            ],
            [
              120.84066009600008,
              17.087560654000185
            ],
            [
              120.83895873900008,
              17.088279725000064
            ],
            [
              120.83778381400009,
              17.08879089400017
            ],
            [
              120.83679199200014,
              17.089239120000116
            ],
            [
              120.83482360800019,
              17.090589523000062
            ],
            [
              120.83537292400013,
              17.08876037700003
            ],
            [
              120.83538055400004,
              17.087999344000025
            ],
            [
              120.83513641300021,
              17.087429047
            ],
            [
              120.83434295600023,
              17.086229324000158
            ],
            [
              120.83354950000012,
              17.08498001000015
            ],
            [
              120.83262634200025,
              17.083360672000083
            ],
            [
              120.8320999150003,
              17.081720352000104
            ],
            [
              120.83130645800009,
              17.079280853000114
            ],
            [
              120.8304061880001,
              17.076860427000042
            ],
            [
              120.82953643800022,
              17.07364082400005
            ],
            [
              120.82984924200002,
              17.071460724000133
            ],
            [
              120.8297882070002,
              17.069810867000115
            ],
            [
              120.82967376700014,
              17.067710876000035
            ],
            [
              120.82933807300003,
              17.065319061000082
            ],
            [
              120.82913970900017,
              17.063690185000155
            ],
            [
              120.82891082800018,
              17.062730790000103
            ],
            [
              120.82885742100007,
              17.06246948300003
            ],
            [
              120.83709716700002,
              17.061399460000075
            ],
            [
              120.84294891400009,
              17.060600280000187
            ],
            [
              120.84567260600022,
              17.065309526000135
            ],
            [
              120.84967803900008,
              17.069499970000095
            ],
            [
              120.85118866000005,
              17.07265091000005
            ],
            [
              120.85344696000004,
              17.075170518000107
            ],
            [
              120.85518646200012,
              17.077270509000073
            ],
            [
              120.85720062200016,
              17.078319550000117
            ],
            [
              120.86096191500008,
              17.080419541000026
            ],
            [
              120.85913849000008,
              17.081550599000025
            ],
            [
              120.85868835400015,
              17.08179092299997
            ]
          ]
        ]
      },
      "properties": {
        "GID_3": "PHL.50.3.3_1",
        "GID_0": "PHL",
        "COUNTRY": "Philippines",
        "GID_1": "PHL.50_1",
        "NAME_1": "Mountain Province",
        "NL_NAME_1": "NA",
        "GID_2": "PHL.50.3_1",
        "NAME_2": "Besao",
        "NL_NAME_2": "NA",
        "NAME_3": "Banguitan",
        "VARNAME_3": "NA",
        "NL_NAME_3": "NA",
        "TYPE_3": "Barangay",
        "ENGTYPE_3": "Village",
        "CC_3": "NA",
        "HASC_3": "NA"
      }
    },
    {
      "type": "Feature",
      "geometry": {
        "type": "Polygon",
        "coordinates": [
          [
            [
              120.86228179900002,
              17.057649612000148
            ],
            [
              120.86454773000003,
              17.061599732000104
            ],
            [
              120.86781311100026,
              17.067899705000116
            ],
            [
              120.87132263100023,
              17.07313919000012
            ],
            [
              120.87458038300008,
              17.0785999310001
            ],
            [
              120.87534332200005,
              17.082160950000116
            ],
            [
              120.87583923300019,
              17.088239670000007
            ],
            [
              120.87834167500012,
              17.095369339000115
            ],
            [
              120.8798522950002,
              17.103969575000065
            ],
            [
              120.87777710000023,
              17.102479935000133
            ],
            [
              120.87600708000014,
              17.100009919
            ],
            [
              120.87452697800006,
              17.09852981500012
            ],
            [
              120.8737869260001,
              17.0934906010001
            ],
            [
              120.87227630600012,
              17.088029862999974
            ],
            [
              120.86950683600003,
              17.08237075800008
            ],
            [
              120.86750793400017,
              17.080480576000184
            ],
            [
              120.86601257400002,
              17.077539444000024
            ],
            [
              120.86475372300004,
              17.073549272000093
            ],
            [
              120.86324310200007,
              17.06893920900012
            ],
            [
              120.86097717300004,
              17.065999985000133
            ],
            [
              120.85846710300007,
              17.062639236000166
            ],
            [
              120.85639190600023,
              17.058660507000184
            ],
            [
              120.85942840600012,
              17.058269500999984
            ],
            [
              120.86228179900002,
              17.057649612000148
            ]
          ]
        ]
      },
      "properties": {
        "GID_3": "PHL.50.3.4_1",
        "GID_0": "PHL",
        "COUNTRY": "Philippines",
        "GID_1": "PHL.50_1",
        "NAME_1": "Mountain Province",
        "NL_NAME_1": "NA",
        "GID_2": "PHL.50.3_1",
        "NAME_2": "Besao",
        "NL_NAME_2": "NA",
        "NAME_3": "Besao East",
        "VARNAME_3": "Besao Proper",
        "NL_NAME_3": "NA",
        "TYPE_3": "Barangay",
        "ENGTYPE_3": "Village",
        "CC_3": "NA",
        "HASC_3": "NA"
      }
    },
    {
      "type": "Feature",
      "geometry": {
        "type": "Polygon",
        "coordinates": [
          [
            [
              120.84294891400009,
              17.060600280000187
            ],
            [
              120.8515090950001,
              17.059499741000025
            ],
            [
              120.85639190600023,
              17.058660507000184
            ],
            [
              120.85846710300007,
              17.062639236000166
            ],
            [
              120.86097717300004,
              17.065999985000133
            ],
            [
              120.86324310200007,
              17.06893920900012
            ],
            [
              120.86475372300004,
              17.073549272000093
            ],
            [
              120.86601257400002,
              17.077539444000024
            ],
            [
              120.86750793400017,
              17.080480576000184
            ],
            [
              120.86950683600003,
              17.08237075800008
            ],
            [
              120.87227630600012,
              17.088029862999974
            ],
            [
              120.8737869260001,
              17.0934906010001
            ],
            [
              120.87452697800006,
              17.09852981500012
            ],
            [
              120.87177276700015,
              17.095609665000097
            ],
            [
              120.87117767400002,
              17.09486007800018
            ],
            [
              120.87104797300003,
              17.093709946000047
            ],
            [
              120.86974334700005,
              17.091470719000142
            ],
            [
              120.86750030400003,
              17.088300706000098
            ],
            [
              120.86595916700003,
              17.086790085000075
            ],
            [
              120.86470031800002,
              17.086389541000187
            ],
            [
              120.86308288500004,
              17.08588981700001
            ],
            [
              120.86157226600005,
              17.084169387000145
            ],
            [
              120.86087036100014,
              17.083040237000148
            ],
            [
              120.8602218630001,
              17.082460404000074
            ],
            [
              120.85868835400015,
              17.08179092299997
            ],
            [
              120.85913849000008,
              17.081550599000025
            ],
            [
              120.86096191500008,
              17.080419541000026
            ],
            [
              120.85720062200016,
              17.078319550000117
            ],
            [
              120.85518646200012,
              17.077270509000073
            ],
            [
              120.85344696000004,
              17.075170518000107
            ],
            [
              120.85118866000005,
              17.07265091000005
            ],
            [
              120.84967803900008,
              17.069499970000095
            ],
            [
              120.84567260600022,
              17.065309526000135
            ],
            [
              120.84294891400009,
              17.060600280000187
            ]
          ]
        ]
      },
      "properties": {
        "GID_3": "PHL.50.3.5_1",
        "GID_0": "PHL",
        "COUNTRY": "Philippines",
        "GID_1": "PHL.50_1",
        "NAME_1": "Mountain Province",
        "NL_NAME_1": "NA",
        "GID_2": "PHL.50.3_1",
        "NAME_2": "Besao",
        "NL_NAME_2": "NA",
        "NAME_3": "Besao West",
        "VARNAME_3": "NA",
        "NL_NAME_3": "NA",
        "TYPE_3": "Barangay",
        "ENGTYPE_3": "Village",
        "CC_3": "NA",
        "HASC_3": "NA"
      }
    },
    {
      "type": "Feature",
      "geometry": {
        "type": "Polygon",
        "coordinates": [
          [
            [
              120.83482360800019,
              17.090589523000062
            ],
            [
              120.83451080300017,
              17.090909958000168
            ],
            [
              120.83400726200011,
              17.09132003700006
            ],
            [
              120.83245086700003,
              17.09288025000012
            ],
            [
              120.83139038200011,
              17.094200135000165
            ],
            [
              120.82968139700006,
              17.095380783000167
            ],
            [
              120.82853698800011,
              17.09555053800011
            ],
            [
              120.82774353100012,
              17.095649720000097
            ],
            [
              120.82678222600009,
              17.09568977400005
            ],
            [
              120.82586669800003,
              17.095609665000097
            ],
            [
              120.82521057200006,
              17.095710755000084
            ],
            [
              120.82463073800022,
              17.096260071000074
            ],
            [
              120.82436370800019,
              17.09668922400016
            ],
            [
              120.82422637900004,
              17.097730637000097
            ],
            [
              120.82392883200009,
              17.09923935000012
            ],
            [
              120.82348632900016,
              17.099670410999977
            ],
            [
              120.82216644200003,
              17.10016059900005
            ],
            [
              120.82063293500028,
              17.100740433000055
            ],
            [
              120.81886291500007,
              17.10144996700018
            ],
            [
              120.8169403070001,
              17.10214042700011
            ],
            [
              120.81561279300001,
              17.101779937000117
            ],
            [
              120.81463623000002,
              17.10116958600014
            ],
            [
              120.81401062000009,
              17.10070991500004
            ],
            [
              120.81363678000002,
              17.10047912600004
            ],
            [
              120.81137084900024,
              17.100219727000137
            ],
            [
              120.8096694940001,
              17.100130082000078
            ],
            [
              120.80795288100023,
              17.100130082000078
            ],
            [
              120.80840301500018,
              17.097560882000153
            ],
            [
              120.808647156,
              17.09428024300007
            ],
            [
              120.80718231200001,
              17.09222030700016
            ],
            [
              120.80619049100005,
              17.089759827000137
            ],
            [
              120.8049621580002,
              17.087499618000095
            ],
            [
              120.8049621580002,
              17.084419251000043
            ],
            [
              120.80568695000011,
              17.081550599000025
            ],
            [
              120.80470275900007,
              17.078670502000023
            ],
            [
              120.80299377400002,
              17.076820373000146
            ],
            [
              120.80200195200018,
              17.073530198000128
            ],
            [
              120.80175781300011,
              17.069629668000175
            ],
            [
              120.80248260500002,
              17.06675910900003
            ],
            [
              120.80355835000034,
              17.06351089400016
            ],
            [
              120.81079101600017,
              17.063360214000113
            ],
            [
              120.82032775900007,
              17.062780380000106
            ],
            [
              120.82698059000018,
              17.06246948300003
            ],
            [
              120.82885742100007,
              17.06246948300003
            ],
            [
              120.82891082800018,
              17.062730790000103
            ],
            [
              120.82913970900017,
              17.063690185000155
            ],
            [
              120.82933807300003,
              17.065319061000082
            ],
            [
              120.82967376700014,
              17.067710876000035
            ],
            [
              120.8297882070002,
              17.069810867000115
            ],
            [
              120.82984924200002,
              17.071460724000133
            ],
            [
              120.82953643800022,
              17.07364082400005
            ],
            [
              120.8304061880001,
              17.076860427000042
            ],
            [
              120.83130645800009,
              17.079280853000114
            ],
            [
              120.8320999150003,
              17.081720352000104
            ],
            [
              120.83262634200025,
              17.083360672000083
            ],
            [
              120.83354950000012,
              17.08498001000015
            ],
            [
              120.83434295600023,
              17.086229324000158
            ],
            [
              120.83513641300021,
              17.087429047
            ],
            [
              120.83538055400004,
              17.087999344000025
            ],
            [
              120.83537292400013,
              17.08876037700003
            ],
            [
              120.83482360800019,
              17.090589523000062
            ]
          ]
        ]
      },
      "properties": {
        "GID_3": "PHL.50.3.6_1",
        "GID_0": "PHL",
        "COUNTRY": "Philippines",
        "GID_1": "PHL.50_1",
        "NAME_1": "Mountain Province",
        "NL_NAME_1": "NA",
        "GID_2": "PHL.50.3_1",
        "NAME_2": "Besao",
        "NL_NAME_2": "NA",
        "NAME_3": "Catengan",
        "VARNAME_3": "NA",
        "NL_NAME_3": "NA",
        "TYPE_3": "Barangay",
        "ENGTYPE_3": "Village",
        "CC_3": "NA",
        "HASC_3": "NA"
      }
    },
    {
      "type": "Feature",
      "geometry": {
        "type": "Polygon",
        "coordinates": [
          [
            [
              120.87728881800012,
              17.189260484000044
            ],
            [
              120.86634826700003,
              17.145589828000027
            ],
            [
              120.86461639400022,
              17.14118003900012
            ],
            [
              120.86431121700002,
              17.13715934800007
            ],
            [
              120.86441039900012,
              17.13497924800015
            ],
            [
              120.86440277100019,
              17.134609222999984
            ],
            [
              120.86451721200001,
              17.133169175000035
            ],
            [
              120.8644332880001,
              17.131010057000083
            ],
            [
              120.86354064900024,
              17.12863922100007
            ],
            [
              120.86389923000002,
              17.127119065000045
            ],
            [
              120.86415863000013,
              17.125270843000067
            ],
            [
              120.86437225300017,
              17.122949599000037
            ],
            [
              120.86411285300017,
              17.120899200999986
            ],
            [
              120.86389160200008,
              17.118890762000035
            ],
            [
              120.86396026600005,
              17.116840363000108
            ],
            [
              120.86392211900022,
              17.11603927600015
            ],
            [
              120.86341858000003,
              17.114259720000177
            ],
            [
              120.86868286200001,
              17.111709595000093
            ],
            [
              120.86958312900003,
              17.116149903000178
            ],
            [
              120.87963104200014,
              17.125049590000117
            ],
            [
              120.87756347600009,
              17.140550614000176
            ],
            [
              120.8862533580002,
              17.1878700260001
            ],
            [
              120.87728881800012,
              17.189260484000044
            ]
          ]
        ]
      },
      "properties": {
        "GID_3": "PHL.50.3.7_1",
        "GID_0": "PHL",
        "COUNTRY": "Philippines",
        "GID_1": "PHL.50_1",
        "NAME_1": "Mountain Province",
        "NL_NAME_1": "NA",
        "GID_2": "PHL.50.3_1",
        "NAME_2": "Besao",
        "NL_NAME_2": "NA",
        "NAME_3": "Gueday",
        "VARNAME_3": "NA",
        "NL_NAME_3": "NA",
        "TYPE_3": "Barangay",
        "ENGTYPE_3": "Village",
        "CC_3": "NA",
        "HASC_3": "NA"
      }
    },
    {
      "type": "Feature",
      "geometry": {
        "type": "Polygon",
        "coordinates": [
          [
            [
              120.86868286200001,
              17.111709595000093
            ],
            [
              120.86341858000003,
              17.114259720000177
            ],
            [
              120.86280822700007,
              17.113410950000116
            ],
            [
              120.86160278300031,
              17.11222076400003
            ],
            [
              120.86052704000008,
              17.111059189000116
            ],
            [
              120.85928344700005,
              17.110269546999973
            ],
            [
              120.85855865500002,
              17.11042022700019
            ],
            [
              120.85727691700015,
              17.110839843999997
            ],
            [
              120.85513305700022,
              17.111089706000087
            ],
            [
              120.85228729300013,
              17.110050202000025
            ],
            [
              120.8510437010001,
              17.108709335000015
            ],
            [
              120.85025787400002,
              17.10692977900004
            ],
            [
              120.84973907400001,
              17.105800628000168
            ],
            [
              120.84884643500004,
              17.104249955
            ],
            [
              120.84809875500014,
              17.103229523000152
            ],
            [
              120.84763336100002,
              17.10288047900002
            ],
            [
              120.84633636500018,
              17.095300674000043
            ],
            [
              120.85462188800011,
              17.09359931900019
            ],
            [
              120.85610199000018,
              17.095079423000072
            ],
            [
              120.85787963800021,
              17.094100952000076
            ],
            [
              120.86083221400008,
              17.098049165000134
            ],
            [
              120.87177276700015,
              17.095609665000097
            ],
            [
              120.87088775500013,
              17.098209382000164
            ],
            [
              120.8697509770002,
              17.10094070500014
            ],
            [
              120.86887359600018,
              17.108339310000076
            ],
            [
              120.86868286200001,
              17.111709595000093
            ]
          ]
        ]
      },
      "properties": {
        "GID_3": "PHL.50.3.8_1",
        "GID_0": "PHL",
        "COUNTRY": "Philippines",
        "GID_1": "PHL.50_1",
        "NAME_1": "Mountain Province",
        "NL_NAME_1": "NA",
        "GID_2": "PHL.50.3_1",
        "NAME_2": "Besao",
        "NL_NAME_2": "NA",
        "NAME_3": "Kin-Iway",
        "VARNAME_3": "Poblacion",
        "NL_NAME_3": "NA",
        "TYPE_3": "Barangay",
        "ENGTYPE_3": "Village",
        "CC_3": "NA",
        "HASC_3": "NA"
      }
    },
    {
      "type": "Feature",
      "geometry": {
        "type": "Polygon",
        "coordinates": [
          [
            [
              120.86887359600018,
              17.108339310000076
            ],
            [
              120.8697509770002,
              17.10094070500014
            ],
            [
              120.87088775500013,
              17.098209382000164
            ],
            [
              120.87177276700015,
              17.095609665000097
            ],
            [
              120.87452697800006,
              17.09852981500012
            ],
            [
              120.87600708000014,
              17.100009919
            ],
            [
              120.87777710000023,
              17.102479935000133
            ],
            [
              120.8798522950002,
              17.103969575000065
            ],
            [
              120.88192749000007,
              17.107189178000112
            ],
            [
              120.88128662000031,
              17.111829758
            ],
            [
              120.86887359600018,
              17.108339310000076
            ]
          ]
        ]
      },
      "properties": {
        "GID_3": "PHL.50.3.9_1",
        "GID_0": "PHL",
        "COUNTRY": "Philippines",
        "GID_1": "PHL.50_1",
        "NAME_1": "Mountain Province",
        "NL_NAME_1": "NA",
        "GID_2": "PHL.50.3_1",
        "NAME_2": "Besao",
        "NL_NAME_2": "NA",
        "NAME_3": "Lacmaan",
        "VARNAME_3": "NA",
        "NL_NAME_3": "NA",
        "TYPE_3": "Barangay",
        "ENGTYPE_3": "Village",
        "CC_3": "NA",
        "HASC_3": "NA"
      }
    },
    {
      "type": "Feature",
      "geometry": {
        "type": "Polygon",
        "coordinates": [
          [
            [
              120.77522277800028,
              17.063299179000126
            ],
            [
              120.78244018600003,
              17.063110353000127
            ],
            [
              120.78546142500022,
              17.06306076000004
            ],
            [
              120.78801727200005,
              17.06300926300014
            ],
            [
              120.79046630900007,
              17.06310081500004
            ],
            [
              120.79486846800023,
              17.063270570000157
            ],
            [
              120.80355835000034,
              17.06351089400016
            ],
            [
              120.80248260500002,
              17.06675910900003
            ],
            [
              120.80175781300011,
              17.069629668000175
            ],
            [
              120.80200195200018,
              17.073530198000128
            ],
            [
              120.80299377400002,
              17.076820373000146
            ],
            [
              120.80470275900007,
              17.078670502000023
            ],
            [
              120.80568695000011,
              17.081550599000025
            ],
            [
              120.8049621580002,
              17.084419251000043
            ],
            [
              120.8049621580002,
              17.087499618000095
            ],
            [
              120.80619049100005,
              17.089759827000137
            ],
            [
              120.80718231200001,
              17.09222030700016
            ],
            [
              120.808647156,
              17.09428024300007
            ],
            [
              120.80840301500018,
              17.097560882000153
            ],
            [
              120.80795288100023,
              17.100130082000078
            ],
            [
              120.806716918,
              17.100139618000185
            ],
            [
              120.8062286380001,
              17.100179672000138
            ],
            [
              120.80564880300005,
              17.100570678000167
            ],
            [
              120.80413818300008,
              17.101629258000173
            ],
            [
              120.80246734700006,
              17.102619172000175
            ],
            [
              120.80081176700003,
              17.103380204000075
            ],
            [
              120.79911804200015,
              17.103689194000083
            ],
            [
              120.79782867400002,
              17.10339927800004
            ],
            [
              120.79541778600003,
              17.103000642000097
            ],
            [
              120.79456329400023,
              17.103630066000164
            ],
            [
              120.7939910890002,
              17.104709625000055
            ],
            [
              120.79385376000016,
              17.10503006000016
            ],
            [
              120.79340362500011,
              17.10530090399999
            ],
            [
              120.79237365600022,
              17.105810166000026
            ],
            [
              120.7909317010002,
              17.106830597
            ],
            [
              120.78970336900022,
              17.107940674000133
            ],
            [
              120.78910064800016,
              17.10857963600006
            ],
            [
              120.78764343200021,
              17.108560562000093
            ],
            [
              120.78054809500009,
              17.110370637000187
            ],
            [
              120.77886200000012,
              17.103029251000066
            ],
            [
              120.77745056200001,
              17.09577941900011
            ],
            [
              120.77675628700024,
              17.09099006700012
            ],
            [
              120.77557373100012,
              17.083370209000122
            ],
            [
              120.77433776900011,
              17.075290681000013
            ],
            [
              120.77522277800028,
              17.063299179000126
            ]
          ]
        ]
      },
      "properties": {
        "GID_3": "PHL.50.3.10_1",
        "GID_0": "PHL",
        "COUNTRY": "Philippines",
        "GID_1": "PHL.50_1",
        "NAME_1": "Mountain Province",
        "NL_NAME_1": "NA",
        "GID_2": "PHL.50.3_1",
        "NAME_2": "Besao",
        "NL_NAME_2": "NA",
        "NAME_3": "Laylaya",
        "VARNAME_3": "NA",
        "NL_NAME_3": "NA",
        "TYPE_3": "Barangay",
        "ENGTYPE_3": "Village",
        "CC_3": "NA",
        "HASC_3": "NA"
      }
    },
    {
      "type": "Feature",
      "geometry": {
        "type": "Polygon",
        "coordinates": [
          [
            [
              120.83419036800001,
              17.100570678000167
            ],
            [
              120.83296203600014,
              17.10095024100019
            ],
            [
              120.83135986300022,
              17.101270676000127
            ],
            [
              120.82997131300021,
              17.101600646999998
            ],
            [
              120.82795715400027,
              17.101369857999998
            ],
            [
              120.82666015500001,
              17.10070991500004
            ],
            [
              120.82512664800004,
              17.100030900000093
            ],
            [
              120.82392883200009,
              17.09923935000012
            ],
            [
              120.82422637900004,
              17.097730637000097
            ],
            [
              120.82436370800019,
              17.09668922400016
            ],
            [
              120.82463073800022,
              17.096260071000074
            ],
            [
              120.82521057200006,
              17.095710755000084
            ],
            [
              120.82586669800003,
              17.095609665000097
            ],
            [
              120.82678222600009,
              17.09568977400005
            ],
            [
              120.82774353100012,
              17.095649720000097
            ],
            [
              120.82853698800011,
              17.09555053800011
            ],
            [
              120.82968139700006,
              17.095380783000167
            ],
            [
              120.83139038200011,
              17.094200135000165
            ],
            [
              120.83245086700003,
              17.09288025000012
            ],
            [
              120.83400726200011,
              17.09132003700006
            ],
            [
              120.83451080300017,
              17.090909958000168
            ],
            [
              120.83482360800019,
              17.090589523000062
            ],
            [
              120.83679199200014,
              17.089239120000116
            ],
            [
              120.83778381400009,
              17.08879089400017
            ],
            [
              120.83895873900008,
              17.088279725000064
            ],
            [
              120.84066009600008,
              17.087560654000185
            ],
            [
              120.84236907900004,
              17.08691024799998
            ],
            [
              120.84414672900004,
              17.08735084600005
            ],
            [
              120.84639740000011,
              17.087720870999988
            ],
            [
              120.84703064000018,
              17.087240219000023
            ],
            [
              120.84809112500022,
              17.086080552000112
            ],
            [
              120.85462188800011,
              17.09359931900019
            ],
            [
              120.84633636500018,
              17.095300674000043
            ],
            [
              120.84763336100002,
              17.10288047900002
            ],
            [
              120.84612274200015,
              17.10224914700001
            ],
            [
              120.84387970000023,
              17.101650239000037
            ],
            [
              120.84068298300008,
              17.101289749000046
            ],
            [
              120.83939361500018,
              17.10165977400004
            ],
            [
              120.83817291200035,
              17.101739883000164
            ],
            [
              120.83750152600021,
              17.10164070100012
            ],
            [
              120.83696746800013,
              17.101270676000127
            ],
            [
              120.83550262500012,
              17.100610733000167
            ],
            [
              120.83419036800001,
              17.100570678000167
            ]
          ]
        ]
      },
      "properties": {
        "GID_3": "PHL.50.3.11_1",
        "GID_0": "PHL",
        "COUNTRY": "Philippines",
        "GID_1": "PHL.50_1",
        "NAME_1": "Mountain Province",
        "NL_NAME_1": "NA",
        "GID_2": "PHL.50.3_1",
        "NAME_2": "Besao",
        "NL_NAME_2": "NA",
        "NAME_3": "Padangan",
        "VARNAME_3": "NA",
        "NL_NAME_3": "NA",
        "TYPE_3": "Barangay",
        "ENGTYPE_3": "Village",
        "CC_3": "NA",
        "HASC_3": "NA"
      }
    },
    {
      "type": "Feature",
      "geometry": {
        "type": "Polygon",
        "coordinates": [
          [
            [
              120.85868835400015,
              17.08179092299997
            ],
            [
              120.8602218630001,
              17.082460404000074
            ],
            [
              120.86087036100014,
              17.083040237000148
            ],
            [
              120.86157226600005,
              17.084169387000145
            ],
            [
              120.86308288500004,
              17.08588981700001
            ],
            [
              120.86470031800002,
              17.086389541000187
            ],
            [
              120.86595916700003,
              17.086790085000075
            ],
            [
              120.86750030400003,
              17.088300706000098
            ],
            [
              120.86974334700005,
              17.091470719000142
            ],
            [
              120.87104797300003,
              17.093709946000047
            ],
            [
              120.87117767400002,
              17.09486007800018
            ],
            [
              120.87177276700015,
              17.095609665000097
            ],
            [
              120.86083221400008,
              17.098049165000134
            ],
            [
              120.85787963800021,
              17.094100952000076
            ],
            [
              120.85610199000018,
              17.095079423000072
            ],
            [
              120.85462188800011,
              17.09359931900019
            ],
            [
              120.84809112500022,
              17.086080552000112
            ],
            [
              120.8495025630001,
              17.085300445000087
            ],
            [
              120.8510971080002,
              17.084100724000052
            ],
            [
              120.85315704400011,
              17.083269120000182
            ],
            [
              120.85498809800004,
              17.082860946000153
            ],
            [
              120.8570327760001,
              17.082170486000052
            ],
            [
              120.85868835400015,
              17.08179092299997
            ]
          ]
        ]
      },
      "properties": {
        "GID_3": "PHL.50.3.12_1",
        "GID_0": "PHL",
        "COUNTRY": "Philippines",
        "GID_1": "PHL.50_1",
        "NAME_1": "Mountain Province",
        "NL_NAME_1": "NA",
        "GID_2": "PHL.50.3_1",
        "NAME_2": "Besao",
        "NL_NAME_2": "NA",
        "NAME_3": "Payeo",
        "VARNAME_3": "NA",
        "NL_NAME_3": "NA",
        "TYPE_3": "Barangay",
        "ENGTYPE_3": "Village",
        "CC_3": "NA",
        "HASC_3": "NA"
      }
    },
    {
      "type": "Feature",
      "geometry": {
        "type": "Polygon",
        "coordinates": [
          [
            [
              120.87650299100005,
              17.056299211000066
            ],
            [
              120.87738037200006,
              17.061790466000105
            ],
            [
              120.87860870400004,
              17.067579270000124
            ],
            [
              120.8804473880001,
              17.073379516000102
            ],
            [
              120.88140869100005,
              17.075439453000115
            ],
            [
              120.88297271700014,
              17.07885933000017
            ],
            [
              120.88359069800003,
              17.07980919000005
            ],
            [
              120.8842697150003,
              17.084409713000127
            ],
            [
              120.88436126700003,
              17.088020325000116
            ],
            [
              120.88423156800013,
              17.08894920400013
            ],
            [
              120.88342285200031,
              17.095569611000144
            ],
            [
              120.8837585460002,
              17.097190856999987
            ],
            [
              120.88350677400001,
              17.098779679000188
            ],
            [
              120.88256073000002,
              17.10396003699998
            ],
            [
              120.88192749000007,
              17.107189178000112
            ],
            [
              120.8798522950002,
              17.103969575000065
            ],
            [
              120.87834167500012,
              17.095369339000115
            ],
            [
              120.87583923300019,
              17.088239670000007
            ],
            [
              120.87534332200005,
              17.082160950000116
            ],
            [
              120.87458038300008,
              17.0785999310001
            ],
            [
              120.87132263100023,
              17.07313919000012
            ],
            [
              120.86781311100026,
              17.067899705000116
            ],
            [
              120.86454773000003,
              17.061599732000104
            ],
            [
              120.86228179900002,
              17.057649612000148
            ],
            [
              120.87650299100005,
              17.056299211000066
            ]
          ]
        ]
      },
      "properties": {
        "GID_3": "PHL.50.3.13_1",
        "GID_0": "PHL",
        "COUNTRY": "Philippines",
        "GID_1": "PHL.50_1",
        "NAME_1": "Mountain Province",
        "NL_NAME_1": "NA",
        "GID_2": "PHL.50.3_1",
        "NAME_2": "Besao",
        "NL_NAME_2": "NA",
        "NAME_3": "Suquib",
        "VARNAME_3": "NA",
        "NL_NAME_3": "NA",
        "TYPE_3": "Barangay",
        "ENGTYPE_3": "Village",
        "CC_3": "NA",
        "HASC_3": "NA"
      }
    },
    {
      "type": "Feature",
      "geometry": {
        "type": "Polygon",
        "coordinates": [
          [
            [
              120.78054809500009,
              17.110370637000187
            ],
            [
              120.78764343200021,
              17.108560562000093
            ],
            [
              120.78910064800016,
              17.10857963600006
            ],
            [
              120.78970336900022,
              17.107940674000133
            ],
            [
              120.7909317010002,
              17.106830597
            ],
            [
              120.79237365600022,
              17.105810166000026
            ],
            [
              120.79340362500011,
              17.10530090399999
            ],
            [
              120.79385376000016,
              17.10503006000016
            ],
            [
              120.7939910890002,
              17.104709625000055
            ],
            [
              120.79456329400023,
              17.103630066000164
            ],
            [
              120.79541778600003,
              17.103000642000097
            ],
            [
              120.79782867400002,
              17.10339927800004
            ],
            [
              120.79911804200015,
              17.103689194000083
            ],
            [
              120.80081176700003,
              17.103380204000075
            ],
            [
              120.80246734700006,
              17.102619172000175
            ],
            [
              120.80413818300008,
              17.101629258000173
            ],
            [
              120.80564880300005,
              17.100570678000167
            ],
            [
              120.8062286380001,
              17.100179672000138
            ],
            [
              120.806716918,
              17.100139618000185
            ],
            [
              120.80795288100023,
              17.100130082000078
            ],
            [
              120.8096694940001,
              17.100130082000078
            ],
            [
              120.81137084900024,
              17.100219727000137
            ],
            [
              120.81363678000002,
              17.10047912600004
            ],
            [
              120.81401062000009,
              17.10070991500004
            ],
            [
              120.81463623000002,
              17.10116958600014
            ],
            [
              120.81561279300001,
              17.101779937000117
            ],
            [
              120.8169403070001,
              17.10214042700011
            ],
            [
              120.81886291500007,
              17.10144996700018
            ],
            [
              120.82063293500028,
              17.100740433000055
            ],
            [
              120.82216644200003,
              17.10016059900005
            ],
            [
              120.82348632900016,
              17.099670410999977
            ],
            [
              120.82392883200009,
              17.09923935000012
            ],
            [
              120.82512664800004,
              17.100030900000093
            ],
            [
              120.82666015500001,
              17.10070991500004
            ],
            [
              120.82795715400027,
              17.101369857999998
            ],
            [
              120.82997131300021,
              17.101600646999998
            ],
            [
              120.83135986300022,
              17.101270676000127
            ],
            [
              120.83296203600014,
              17.10095024100019
            ],
            [
              120.83419036800001,
              17.100570678000167
            ],
            [
              120.81440734900013,
              17.15637016300019
            ],
            [
              120.8084869390002,
              17.150190353000085
            ],
            [
              120.80039978000013,
              17.14059066800013
            ],
            [
              120.79102325500014,
              17.127950669000086
            ],
            [
              120.78621673500004,
              17.119390488000136
            ],
            [
              120.78183746300022,
              17.11395073
            ],
            [
              120.78054809500009,
              17.110370637000187
            ]
          ]
        ]
      },
      "properties": {
        "GID_3": "PHL.50.3.14_1",
        "GID_0": "PHL",
        "COUNTRY": "Philippines",
        "GID_1": "PHL.50_1",
        "NAME_1": "Mountain Province",
        "NL_NAME_1": "NA",
        "GID_2": "PHL.50.3_1",
        "NAME_2": "Besao",
        "NL_NAME_2": "NA",
        "NAME_3": "Tamboan",
        "VARNAME_3": "NA",
        "NL_NAME_3": "NA",
        "TYPE_3": "Barangay",
        "ENGTYPE_3": "Village",
        "CC_3": "NA",
        "HASC_3": "NA"
      }
    }
  ]
}